{
  "tasks": [
    {
      "sortId": 0,
      "task": "人参を買いに行く",
      "limit": "2022-02-25",
      "completed": false,
      "completedAt": "9999-12-31",
      "id": 1
    },
    {
      "sortId": 1,
      "task": "玉ねぎを買いに行く",
      "limit": "2022-02-26",
      "completed": false,
      "completedAt": "9999-12-31",
      "id": 2
    },
    {
      "sortId": 2,
      "task": "じゃがいもを買いに行く",
      "limit": "2022-02-25",
      "completed": true,
      "completedAt": "2022-02-25",
      "id": 3
    },
    {
      "sortId": 3,
      "task": "卵を買いに行く",
      "limit": "2022-02-24",
      "completed": false,
      "completedAt": "9999-12-31",
      "id": 4
    },
    {
      "sortId": 3,
      "task": "牛乳を買いに行く",
      "limit": "2022-02-25",
      "completed": true,
      "completedAt": "2022-02-24",
      "id": 5
    }
  ]
}
